colbertfinance/__init__.py
colbertfinance/gui.py
colbertfinance/steps.py
colbertfinance-0.4.9.dist-info/METADATA
colbertfinance-0.4.9.dist-info/WHEEL
colbertfinance-0.4.9.dist-info/top_level.txt
colbertfinance-0.4.9.dist-info/RECORD
