Metadata-Version: 2.1
Name: colbertfinance
Version: 0.4.9
Summary: Librería paso-a-paso para enseñar Markowitz
Author: Jesús Colbert
Project-URL: Homepage, https://pypi.org/project/colbertfinance
Requires-Python: >=3.9
Requires-Dist: pandas
Requires-Dist: numpy
Requires-Dist: yfinance
Requires-Dist: openpyxl
